api_client/__init__.py
api_client/api_client.py
api_client/async_api_client.py
api_client/bearer_token_auth.py
api_client/hooks.py
api_client/status_code_method.py
allure_api_client-26.15.dist-info/METADATA
allure_api_client-26.15.dist-info/WHEEL
allure_api_client-26.15.dist-info/licenses/LICENSE
allure_api_client-26.15.dist-info/RECORD
