Metadata-Version: 2.4
Name: allure-api-client
Version: 26.15
Summary: API Client for Python ^3.10 and Pytest projects. It includes the Allure request/response hooks and the status code checking inside the main method. Request hook generates cURL, Response hook represents the useful information.
License: MIT
License-File: LICENSE
Author: amaym0n
Author-email: loco.skitls@gmail.com
Classifier: License :: OSI Approved :: MIT License
Classifier: Programming Language :: Python :: 2
Classifier: Programming Language :: Python :: 2.7
Classifier: Programming Language :: Python :: 3
Classifier: Programming Language :: Python :: 3.4
Classifier: Programming Language :: Python :: 3.5
Classifier: Programming Language :: Python :: 3.6
Classifier: Programming Language :: Python :: 3.7
Classifier: Programming Language :: Python :: 3.8
Classifier: Programming Language :: Python :: 3.9
Classifier: Programming Language :: Python :: 3.10
Classifier: Programming Language :: Python :: 3.11
Classifier: Programming Language :: Python :: 3.12
Classifier: Programming Language :: Python :: 3.13
Classifier: Programming Language :: Python :: 3.14
Requires-Dist: allure-pytest ; python_version >= "3.11" and python_version < "4.0"
Requires-Dist: httpx ; python_version >= "3.11" and python_version < "4.0"
Requires-Dist: httpx-auth ; python_version >= "3.11" and python_version < "4.0"
Requires-Dist: pydantic ; python_version >= "3.11" and python_version < "4.0"
